FastqToFastaConverter/__init__.py
FastqToFastaConverter/fastq2fasta.py
FastqToFastaConverter-0.1.dist-info/LICENSE.txt
FastqToFastaConverter-0.1.dist-info/METADATA
FastqToFastaConverter-0.1.dist-info/WHEEL
FastqToFastaConverter-0.1.dist-info/top_level.txt
FastqToFastaConverter-0.1.dist-info/RECORD
